Elements/Compounds.py
Elements/EnergyLib.py
Elements/__init__.py
Elements/__version__.py
Elements/colours.txt
compwizard-1.0.3.3.dist-info/METADATA
compwizard-1.0.3.3.dist-info/WHEEL
compwizard-1.0.3.3.dist-info/top_level.txt
compwizard-1.0.3.3.dist-info/RECORD
