Metadata-Version: 2.1
Name: compwizard
Version: 1.0.3.3
Summary: Creates virtual compounds with properties based on xraylib. Compound wizard is a package from XISMuS software.
Home-page: https://github.com/linssab/XISMuS
Author: Sergio A. B. Lins
Author-email: sergio.lins@roma3.infn.it
License: MIT
Platform: UNKNOWN
Requires-Dist: numpy (>=1.18.1)
